README.rst
setup.py
zomathon/__init__.py
zomathon/zomathon.py
zomathon.egg-info/PKG-INFO
zomathon.egg-info/SOURCES.txt
zomathon.egg-info/dependency_links.txt
zomathon.egg-info/not-zip-safe
zomathon.egg-info/top_level.txt