Metadata-Version: 1.1
Name: zomathon
Version: 1.4
Summary: Zomato API Python Module
Home-page: https://github.com/abhishtagatya/zomathon
Author: abhishtagatya
Author-email: gatya.dev@yahoo.com
License: MIT
Platform: UNKNOWN
Classifier: Programming Language :: Python :: 3
Classifier: License :: OSI Approved :: MIT License
Classifier: Operating System :: OS Independent
